pyminer_norm/__init__.py
pyminer_norm/analyze_chromium_h5.py
pyminer_norm/col_sums.py
pyminer_norm/combine_col_sums_counts.py
pyminer_norm/common_functions.py
pyminer_norm/concatenate_matricies_by_col.py
pyminer_norm/downsample.py
pyminer_norm/filter_count_sums_ds_merge_log.py
pyminer_norm/log2_transform.py
pyminer_norm/malat1_and_mito_filter.py
pyminer_norm/mtx_read_qunat_filter.py
pyminer_norm/process_chromium_h5.py
pyminer_norm/quantile_normalize.py
pyminer_norm/random_downsample_whole_dataset.py
pyminer_norm/remove_columns.py
pyminer_norm/split_big_file.py
pyminer_norm/split_dataset_for_cv.py
bio_pyminer_norm-0.2.6.dist-info/METADATA
bio_pyminer_norm-0.2.6.dist-info/WHEEL
bio_pyminer_norm-0.2.6.dist-info/top_level.txt
bio_pyminer_norm-0.2.6.dist-info/RECORD
