Metadata-Version: 2.1
Name: bio-pyminer-norm
Version: 0.2.6
Summary: PyMINEr Norm: A normalization package for scRNAseq
Home-page: https://scottyler892@bitbucket.org/scottyler892/pyminer_norm
Author: Scott Tyler
Author-email: scottyler89@gmail.com
License: UNKNOWN
Platform: UNKNOWN
Classifier: Programming Language :: Python :: 3
Classifier: License :: OSI Approved :: GNU Affero General Public License v3
Classifier: Operating System :: OS Independent
Requires-Dist: seaborn (>=0.8.1)
Requires-Dist: numpy (>=1.16.0)
Requires-Dist: scikit-learn
Requires-Dist: h5py (>=2.9.0)
Requires-Dist: matplotlib (>=3.0.2)
Requires-Dist: scipy (>=1.2.0)
Requires-Dist: ray (>=0.8.0)
